HISTORY.rst
LICENSE
MANIFEST.in
README.rst
requirements.txt
setup.py
pygodaddy/__init__.py
pygodaddy/client.py
pygodaddy.egg-info/PKG-INFO
pygodaddy.egg-info/SOURCES.txt
pygodaddy.egg-info/dependency_links.txt
pygodaddy.egg-info/requires.txt
pygodaddy.egg-info/top_level.txt