Metadata-Version: 1.1
Name: pygodaddy
Version: 0.1.6
Summary: 3rd Party Client Library for Manipulating Go Daddy DNS Records.
Home-page: https://github.com/observerss/pygodaddy
Author: Jingchao Hu(observerss)
Author-email: jingchaohu@gmail.com
License: Apache License, Version 2.0
